djingles/__init__.py
djingles/_version.py
djingles/apps.py
djingles/exceptions.py
djingles/pagination.py
djingles/permissions.py
djingles/utils.py
djingles/views.py
djingles/__pycache__/__init__.cpython-310.pyc
djingles/__pycache__/__init__.cpython-36.pyc
djingles/__pycache__/__init__.cpython-38.pyc
djingles/__pycache__/_version.cpython-310.pyc
djingles/__pycache__/_version.cpython-36.pyc
djingles/__pycache__/_version.cpython-38.pyc
djingles/__pycache__/apps.cpython-310.pyc
djingles/__pycache__/apps.cpython-36.pyc
djingles/__pycache__/apps.cpython-38.pyc
djingles/__pycache__/exceptions.cpython-310.pyc
djingles/__pycache__/exceptions.cpython-36.pyc
djingles/__pycache__/exceptions.cpython-38.pyc
djingles/__pycache__/pagination.cpython-310.pyc
djingles/__pycache__/pagination.cpython-36.pyc
djingles/__pycache__/pagination.cpython-38.pyc
djingles/__pycache__/permissions.cpython-310.pyc
djingles/__pycache__/permissions.cpython-36.pyc
djingles/__pycache__/permissions.cpython-38.pyc
djingles/__pycache__/utils.cpython-310.pyc
djingles/__pycache__/utils.cpython-36.pyc
djingles/__pycache__/utils.cpython-38.pyc
djingles/bootstrap4/__init__.py
djingles/bootstrap4/formatters.py
djingles/bootstrap4/models.py
djingles/bootstrap4/urls.py
djingles/bootstrap4/views.py
djingles/bootstrap4/__pycache__/__init__.cpython-310.pyc
djingles/bootstrap4/__pycache__/__init__.cpython-36.pyc
djingles/bootstrap4/__pycache__/__init__.cpython-38.pyc
djingles/bootstrap4/__pycache__/models.cpython-310.pyc
djingles/bootstrap4/__pycache__/models.cpython-36.pyc
djingles/bootstrap4/__pycache__/models.cpython-38.pyc
djingles/bootstrap4/__pycache__/urls.cpython-36.pyc
djingles/bootstrap4/__pycache__/views.cpython-36.pyc
djingles/bootstrap4/forms/__init__.py
djingles/bootstrap4/forms/fields.py
djingles/bootstrap4/forms/widgets.py
djingles/bootstrap4/forms/__pycache__/__init__.cpython-310.pyc
djingles/bootstrap4/forms/__pycache__/__init__.cpython-36.pyc
djingles-0.2.0.dist-info/METADATA
djingles-0.2.0.dist-info/WHEEL
djingles-0.2.0.dist-info/entry_points.txt
djingles-0.2.0.dist-info/top_level.txt
djingles-0.2.0.dist-info/RECORD
