Metadata-Version: 2.1
Name: djingles
Version: 0.2.0
Summary: Set of django utilities
Home-page: https://github.com/vivsh/djingles
License: BSD
Keywords: django utilities
Platform: UNKNOWN
Classifier: Environment :: Web Environment
Classifier: Intended Audience :: Developers
Classifier: License :: OSI Approved :: BSD License
Classifier: Operating System :: OS Independent
Classifier: Programming Language :: Python :: 3
Classifier: Topic :: Internet :: WWW/HTTP :: Dynamic Content
Classifier: Topic :: Software Development :: Libraries :: Python Modules
Classifier: Topic :: Text Processing :: Markup :: HTML
Requires-Python: >=3
Requires-Dist: django (>=4)
Requires-Dist: djangorestframework
Requires-Dist: jinja2 (>=3)
Requires-Dist: python-dateutil
